lrmcs.cp312-win_amd64.pyd
setup.py
lrmcs-0.1.0.dist-info/licenses/LICENSE
lrmcs-0.1.0.dist-info/METADATA
lrmcs-0.1.0.dist-info/WHEEL
lrmcs-0.1.0.dist-info/top_level.txt
lrmcs-0.1.0.dist-info/RECORD
