Metadata-Version: 2.4
Name: LRMCS
Version: 0.1.0
Summary: A simple example of a pybind11 module using pyproject.toml and setup.py
Author-email: Felipe Martins Silveira Lima <felipe.mslima07@usp.br>
License: MIT License
Project-URL: Homepage, https://github.com/LabRisco/LRMCS
Keywords: pybind11,cpp,python
Requires-Python: <3.13,>=3.8
License-File: LICENSE
Dynamic: license-file
